gateway_manager/__init__.py
gateway_manager/api.py
gateway_manager/devserver.py
gateway_manager/gateway.py
gateway_manager/generate_function.py
gateway_manager/importer.py
gateway_manager/scripts.py
gateway_manager-0.1.0.dist-info/DESCRIPTION.rst
gateway_manager-0.1.0.dist-info/entry_points.txt
gateway_manager-0.1.0.dist-info/METADATA
gateway_manager-0.1.0.dist-info/metadata.json
gateway_manager-0.1.0.dist-info/RECORD
gateway_manager-0.1.0.dist-info/top_level.txt
gateway_manager-0.1.0.dist-info/WHEEL
