Metadata-Version: 2.0
Name: gateway-manager
Version: 0.1.0
Summary: Manage your api gateway and lambda functions with ease.
Home-page: UNKNOWN
Author: Matt George
Author-email: mgeorge@gmail.com
License: UNKNOWN
Platform: UNKNOWN
Requires-Dist: click (==6.3)
Requires-Dist: ramlfications
Requires-Dist: boto3
Requires-Dist: Paste (==2.0.2)
Requires-Dist: Routes (>=2.2)
Requires-Dist: WebOb (==1.5.1)
